up_pps/__init__.py
up_pps/converter.py
up_pps/engine.py
up_pps-1.0.0.dist-info/LICENSE
up_pps-1.0.0.dist-info/METADATA
up_pps-1.0.0.dist-info/WHEEL
up_pps-1.0.0.dist-info/top_level.txt
up_pps-1.0.0.dist-info/RECORD
